[
  {
    "id": "mo9397p8jz2n",
    "label": "Original Owner Form",
    "filename": "mo9397p8jz2n-img20260421_16124652.pdf",
    "fileType": "pdf",
    "size": 241760,
    "uploadedBy": "admin",
    "uploadedAt": "2026-04-21T20:40:51.304Z"
  },
  {
    "id": "mo1w82hzwfuu",
    "label": "Advisor Board   April 13 update",
    "filename": "mo1w82hzwfuu-Advisor_Board_-_April_13_update.pdf",
    "fileType": "pdf",
    "size": 708786,
    "uploadedBy": "admin",
    "uploadedAt": "2026-04-16T19:49:37.899Z"
  }
]